SakuraKnPost/SakuraKnPost.py
SakuraKnPost/__init__.py
skp_debug-0.4.1.dist-info/METADATA
skp_debug-0.4.1.dist-info/WHEEL
skp_debug-0.4.1.dist-info/top_level.txt
skp_debug-0.4.1.dist-info/RECORD
